README.md
setup.py
bookmarks2markdown/__init__.py
bookmarks2markdown/__main__.py
bookmarks2markdown.egg-info/PKG-INFO
bookmarks2markdown.egg-info/SOURCES.txt
bookmarks2markdown.egg-info/dependency_links.txt
bookmarks2markdown.egg-info/entry_points.txt
bookmarks2markdown.egg-info/requires.txt
bookmarks2markdown.egg-info/top_level.txt