Metadata-Version: 2.1
Name: bookmarks2markdown
Version: 1.0.1
Summary: Convert HTML bookmarks to Markdown
Home-page: https://github.com/trubitsyn/bookmarks2markdown
Author: Nikola Trubitsyn
Author-email: nikola.trubitsyn@gmail.com
License: Apache License, Version 2.0
Platform: UNKNOWN
Classifier: License :: OSI Approved :: Apache Software License
Classifier: Programming Language :: Python :: 3.6
Requires-Python: >=3.6
